Metadata-Version: 1.0
Name: ximenez
Version: 0.9
Summary: The purpose of Ximenez is to execute an action on a set of collected items. Both the action and the way items are collected, are defined by Python modules, which are called plug-ins.
Home-page: http://code.noherring.com/ximenez
Author: Damien Baty
Author-email: damien.baty@remove-me.gmail.com
License: GNU GPL
Download-URL: http://cheeseshop.python.org/pypi/ximenez
Keywords: collector action plug-in plugin
Platform: UNKNOWN
Classifier: Development Status :: 4 - Beta
Classifier: Intended Audience :: Developers
Classifier: Intended Audience :: System Administrators
Classifier: License :: OSI Approved :: GNU General Public License (GPL)
Classifier: Operating System :: OS Independent
Classifier: Programming Language :: Python
Classifier: Topic :: System
Classifier: Topic :: Utilities
